pypsm/__init__.py
pypsm/rdp.py
pypsm/version.py
cybr_pypsm-1.0.6.dist-info/LICENSE
cybr_pypsm-1.0.6.dist-info/METADATA
cybr_pypsm-1.0.6.dist-info/WHEEL
cybr_pypsm-1.0.6.dist-info/top_level.txt
cybr_pypsm-1.0.6.dist-info/RECORD
