Metadata-Version: 2.1
Name: cybr-pypsm
Version: 1.0.6
Summary: CyberArk Privileged Session Manager RDPFile Generator
Home-page: https://github.com/infamousjoeg/pypsm
Author: Joe Garcia
Author-email: joe.garcia@cyberark.com
License: MIT
Project-URL: Bug Reports, https://github.com/infamousjoeg/pypsm/issues/new?assignees=&labels=&template=bug_report.md&title=
Project-URL: Feature Requests, https://github.com/infamousjoeg/pypsm/issues/new?assignees=&labels=&template=feature_request.md&title=
Project-URL: Source, https://github.com/infamousjoeg/pypsm
Keywords: cyberark,security,vault,psm,rdp,privileged access,identity,pam,pim,pas
Platform: UNKNOWN
Classifier: Programming Language :: Python :: 3 :: Only
Classifier: Development Status :: 4 - Beta
Classifier: Intended Audience :: Developers
Classifier: License :: OSI Approved :: MIT License
Classifier: Operating System :: OS Independent
Classifier: Natural Language :: English
Classifier: Topic :: Office/Business
Classifier: Topic :: Security
Classifier: Topic :: Security :: Cryptography
Classifier: Topic :: Software Development
Classifier: Topic :: Software Development :: Libraries
Classifier: Topic :: Software Development :: Libraries :: Python Modules
Classifier: Topic :: System :: Systems Administration
Classifier: Topic :: Utilities
